{
  "all_state_fast_oracle_goal_satisfied": false,
  "all_state_fast_oracle_goal_satisfied_by_this_decision": false,
  "allow_unsafe_generation": false,
  "artifact_suffix": "noaws_detached_waitsafe_live_mmap020_dynamic_threads",
  "checked_at_utc": "2026-06-02T02:54:18.086852+00:00",
  "commands": [
    {
      "command": "nice -n 20 /opt/miniconda3/bin/python scripts/generate_h48_tables.py --profile thesis --seed 2026 --solver h48h8 --threads 5 --mmap-output --progress-log --require-safe --min-mmap-available-memory-gib 0.19999999925494194",
      "phase": "generate_table",
      "return_code": -15,
      "runtime_seconds": 1273.728537,
      "stderr_tail": "",
      "stdout_tail": "[H48 gendata] Processed 0 / 7437855 cubes\n[H48 gendata] Processed 0 / 7437855 cubes\n[H48 gendata] Processed 0 / 7437855 cubes\n[H48 gendata] Processed 0 / 7437855 cubes\n[H48 gendata] Processed 0 / 7437855 cubes\n[H48 gendata] Processed 0 / 7437855 cubes\n[H48 gendata] Processed 0 / 7437855 cubes\n[H48 gendata] Processed 0 / 7437855 cubes\n[H48 gendata] Processed 0 / 7437855 cubes\n[H48 gendata] Processed 0 / 7437855 cubes\n[H48 gendata] Processed 0 / 7437855 cubes\n[H48 gendata] Processed 0 / 7437855 cubes\n[H48 gendata] Processed 0 / 7437855 cubes\n[H48 gendata] Processed 0 / 7437855 cubes\n[H48 gendata] Processed 0 / 7437855 cubes\n[H48 gendata] Processed 0 / 7437855 cubes\n[H48 gendata] Processed 0 / 7437855 cubes\n[H48 gendata] Processed 0 / 7437855 cubes\n[H48 gendata] Processed 0 / 7437855 cubes\n[H48 gendata] Processed 0 / 7437855 cubes\n[H48 gendata] Processed 0 / 7437855 cubes\n[H48 gendata] Processed 0 / 7437855 cubes\n[H48 gendata] Processed 0 / 7437855 cubes\n[H48 gendata] Processed 0 / 7437855 cubes\n[H48 gendata] Processed 0 / 7437855 cubes\n[H48 gendata] Processed 0 / 7437855 cubes\n[H48 gendata] Processed 0 / 7437855 cubes\n[H48 gendata] Processed 0 / 7437855 cubes\n[H48 gendata] Processed 0 / 7437855 cubes\n[H48 gendata] Processed 0 / 7437855 cubes\n[H48 gendata] Processed 0 / 7437855 cubes\n[H48 gendata] Processed 0 / 7437855 cubes\n[H48 gendata] Processed 0 / 7437855 cubes\n[H48 gendata] Processed 0 / 7437855 cubes\n[H48 gendata] Processed 0 / 7437855 cubes\n[H48 gendata] Processed 0 / 7437855 cubes\n[H48 gendata] Processed 0 / 7437855 cubes\n[H48 gendata] Processed 0 / 7437855 cubes\n[H48 gendata] Processed 0 / 7437855 cubes\n[H48 gendata] Processed 0 / 7437855 cubes\n[H48 gendata] Processed 0 / 7437855 cubes\n[H48 gendata] Processed 0 / 7437855 cubes\n[H48 gendata] Processed 0 / 7437855 cubes\n[H48 gendata] Processed 0 / 7437855 cubes\n[H48 gendata] Processed 0 / 7437855 cubes\n[H48 gendata] Processed 0 / 7437855 cubes\n[H48 gendata] Processed 0 / 7437855 cubes\n[H48 gendata] Processed 0 / 7437855 cubes\n[H48 gendata] Processed 0 / 7437855 cubes\n[H48 gendata] Processed 0 / 7437855 cubes\n[H48 gendata] Processed 0 / 7437855 cubes\n[H48 gendata] Processed 0 / 7437855 cubes\n[H48 gendata] Processed 0 / 7437855 cubes\n[H48 gendata] Processed 0 / 7437855 cubes\n[H48 gendata] Processed 0 / 7437855 cubes\n[H48 gendata] Processed 0 / 7437855 cubes\n[H48 gendata] Processed 0 / 7437855 cubes\n[H48 gendata] Processed 0 / 7437855 cubes\n[H48 gendata] Processed 0 / 7437855 cubes\n[H48 gendata] Processed 0 / 7437855 cubes\n[H48 gendata] Processed 0 / 7437855 cubes\n[H48 gendata] Processed 0 / 7437855 cubes\n[H48 gendata] Processed 0 / 7437855 cubes\n[H48 gendata] Processed 0 / 7437855 cubes\n[H48 gendata] Processed 0 / 7437855 cubes\n[H48 gendata] Processed 0 / 7437855 cubes\n[H48 gendata] Processed 0 / 7437855 cubes\n[H48 gendata] Processed 0 / 7437855 cubes\n[H48 gendata] Processed 0 / 7437855 cubes\n[H48 gendata] Processed 0 / 7437855 cubes\n[H48 gendata] Processed 0 / 7437855 cubes\n[H48 gendata] Processed 0 / 7437855 cubes\n[H48 gendata] Processed 0 / 7437855 cubes\n[H48 gendata] Processed 0 / 7437855 cubes\n[H48 gendata] Processed 0 / 7437855 cubes\n[H48 gendata] Processed 0 / 7437855 cubes\n[H48 gendata] Processed 0 / 7437855 cubes\n[H48 gendata] Processed 0 / 7437855 cubes\n[H48 gendata] Processed 0 / 7437855 cubes\n[H48 gendata] Processed 0 / 7437855 cubes",
      "streamed_output": true,
      "terminated_process_group": false,
      "timed_out": false
    }
  ],
  "current_next_missing_oracle_grade_solver": "h48h8",
  "current_strongest_local_oracle_solver": "h48h7",
  "dry_run": false,
  "dynamic_thread_selection": true,
  "fast_runtime_proven_for_every_possible_state": false,
  "generation_command": "nice -n 20 /opt/miniconda3/bin/python scripts/generate_h48_tables.py --profile thesis --seed 2026 --solver h48h8 --threads 5 --mmap-output --progress-log --require-safe --min-mmap-available-memory-gib 0.19999999925494194",
  "generation_command_args": [
    "nice",
    "-n",
    "20",
    "/opt/miniconda3/bin/python",
    "scripts/generate_h48_tables.py",
    "--profile",
    "thesis",
    "--seed",
    "2026",
    "--solver",
    "h48h8",
    "--threads",
    "5",
    "--mmap-output",
    "--progress-log",
    "--require-safe",
    "--min-mmap-available-memory-gib",
    "0.19999999925494194"
  ],
  "generation_threads": 5,
  "notes": "Stronger H48 table campaign for the requested fast optimal oracle over every valid 3x3 state. This artifact is deliberately not a completion claim unless the target table is trusted, the full table checksum matches its metadata, hard-case certification passes, broad runtime evidence exists, and a worst-case runtime boundary is documented.",
  "passed": false,
  "post_campaign_checksum_details": {
    "full_checksum_valid": false,
    "metadata_exists": false,
    "metadata_path": "results/processed/h48_metadata_seed_2026_thesis_h48h8.json",
    "table_exists": false,
    "table_path": "data/generated/h48/thesis_seed_2026/h48h8.bin",
    "trusted_metadata_valid": false
  },
  "post_campaign_full_checksum_message": "missing target table or metadata after campaign",
  "post_campaign_full_checksum_valid": false,
  "post_campaign_target_trusted_message": "missing target table or metadata after campaign",
  "post_campaign_target_trusted_table": false,
  "profile": "thesis",
  "remaining_completion_requirements": [
    "trusted h48h8 table metadata and checksum",
    "hard-case exact certification with h48h8",
    "broad arbitrary-state corpus under thesis runtime target with h48h8",
    "formal or supervisor-approved empirical worst-case runtime boundary"
  ],
  "safety": {
    "estimated_table_size_bytes": 7585624040,
    "estimated_table_size_gib": 7.064663,
    "machine": {
      "available_memory_bytes": 299286528,
      "cpu_count": 8,
      "data_generated_h48_free_bytes": 23201181696,
      "load_average": [
        2.93310546875,
        3.0478515625,
        3.09375
      ],
      "memory_bytes": 17179869184
    },
    "policy": {
      "disk_multiplier": 2.0,
      "generation_storage": "mmap_file",
      "load_fraction_limit": 0.5,
      "memory_fraction_limit": 0.35,
      "min_mmap_available_memory_bytes": 214748364,
      "mmap_output": true
    },
    "reasons": [],
    "safe_to_start": true,
    "solver": "h48h8",
    "threads": 5
  },
  "safety_wait": {
    "check_interval_seconds": 60.0,
    "completed_consecutive_checks": 2,
    "final_safety": {
      "estimated_table_size_bytes": 7585624040,
      "estimated_table_size_gib": 7.064663,
      "machine": {
        "available_memory_bytes": 299286528,
        "cpu_count": 8,
        "data_generated_h48_free_bytes": 23201181696,
        "load_average": [
          2.93310546875,
          3.0478515625,
          3.09375
        ],
        "memory_bytes": 17179869184
      },
      "policy": {
        "disk_multiplier": 2.0,
        "generation_storage": "mmap_file",
        "load_fraction_limit": 0.5,
        "memory_fraction_limit": 0.35,
        "min_mmap_available_memory_bytes": 214748364,
        "mmap_output": true
      },
      "reasons": [],
      "safe_to_start": true,
      "solver": "h48h8",
      "threads": 5
    },
    "required_consecutive_checks": 2,
    "safe_to_start": true,
    "sample_count": 3,
    "samples": [
      {
        "dynamic_thread_selection": true,
        "elapsed_seconds": 0.00405,
        "reasons": [
          "available memory 0.18 GiB is below the 0.20 GiB mmap generation guard"
        ],
        "resolved_threads": 5,
        "safe_to_start": false,
        "safety": {
          "estimated_table_size_bytes": 7585624040,
          "estimated_table_size_gib": 7.064663,
          "machine": {
            "available_memory_bytes": 188235776,
            "cpu_count": 8,
            "data_generated_h48_free_bytes": 23203905536,
            "load_average": [
              2.82177734375,
              3.1181640625,
              3.12744140625
            ],
            "memory_bytes": 17179869184
          },
          "policy": {
            "disk_multiplier": 2.0,
            "generation_storage": "mmap_file",
            "load_fraction_limit": 0.5,
            "memory_fraction_limit": 0.35,
            "min_mmap_available_memory_bytes": 214748364,
            "mmap_output": true
          },
          "reasons": [
            "available memory 0.18 GiB is below the 0.20 GiB mmap generation guard"
          ],
          "safe_to_start": false,
          "solver": "h48h8",
          "threads": 5
        },
        "sample_index": 1,
        "thread_setting": "auto"
      },
      {
        "dynamic_thread_selection": true,
        "elapsed_seconds": 60.017363,
        "reasons": [],
        "resolved_threads": 5,
        "safe_to_start": true,
        "safety": {
          "estimated_table_size_bytes": 7585624040,
          "estimated_table_size_gib": 7.064663,
          "machine": {
            "available_memory_bytes": 216203264,
            "cpu_count": 8,
            "data_generated_h48_free_bytes": 23199084544,
            "load_average": [
              3.1015625,
              3.12890625,
              3.12744140625
            ],
            "memory_bytes": 17179869184
          },
          "policy": {
            "disk_multiplier": 2.0,
            "generation_storage": "mmap_file",
            "load_fraction_limit": 0.5,
            "memory_fraction_limit": 0.35,
            "min_mmap_available_memory_bytes": 214748364,
            "mmap_output": true
          },
          "reasons": [],
          "safe_to_start": true,
          "solver": "h48h8",
          "threads": 5
        },
        "sample_index": 2,
        "thread_setting": "auto"
      },
      {
        "dynamic_thread_selection": true,
        "elapsed_seconds": 120.026268,
        "reasons": [],
        "resolved_threads": 5,
        "safe_to_start": true,
        "safety": {
          "estimated_table_size_bytes": 7585624040,
          "estimated_table_size_gib": 7.064663,
          "machine": {
            "available_memory_bytes": 299286528,
            "cpu_count": 8,
            "data_generated_h48_free_bytes": 23201181696,
            "load_average": [
              2.93310546875,
              3.0478515625,
              3.09375
            ],
            "memory_bytes": 17179869184
          },
          "policy": {
            "disk_multiplier": 2.0,
            "generation_storage": "mmap_file",
            "load_fraction_limit": 0.5,
            "memory_fraction_limit": 0.35,
            "min_mmap_available_memory_bytes": 214748364,
            "mmap_output": true
          },
          "reasons": [],
          "safe_to_start": true,
          "solver": "h48h8",
          "threads": 5
        },
        "sample_index": 3,
        "thread_setting": "auto"
      }
    ],
    "status": "safety_wait_passed",
    "timeout_seconds": 43200.0,
    "waited": true
  },
  "schema_version": 1,
  "seed": 2026,
  "should_run_generation": true,
  "status": "generation_failed_or_timed_out",
  "target_estimated_table_size_bytes": 7585624040,
  "target_h_value": 8,
  "target_metadata_path": "results/processed/h48_metadata_seed_2026_thesis_h48h8.json",
  "target_solver": "h48h8",
  "target_table_path": "data/generated/h48/thesis_seed_2026/h48h8.bin",
  "target_trusted_message": "missing target table or metadata",
  "target_trusted_table": false,
  "thread_setting": "auto"
}
