{
  "before_ready": false,
  "checked_at_utc": "2026-05-31T11:47:04.302260+00:00",
  "command": "nice -n 20 /opt/homebrew/bin/pypy3 -c import array as ar\nfrom pathlib import Path\nimport optimal.face\nimport optimal.defs as defs\nimport optimal.enums as enums\nimport optimal.moves as mv\npath = Path('cornerprun')\nif path.exists() and path.stat().st_size == defs.N_CORNERS:\n    print('cornerprun already ready')\nelse:\n    print('creating cornerprun table...')\n    corner_depth = ar.array('b', [-1] * defs.N_CORNERS)\n    corner_depth[0] = 0\n    done = 1\n    depth = 0\n    while done != defs.N_CORNERS:\n        for corners in range(defs.N_CORNERS):\n            if corner_depth[corners] != depth:\n                continue\n            base = defs.N_MOVE * corners\n            for move in enums.Move:\n                corners1 = mv.corners_move[base + move]\n                if corner_depth[corners1] == -1:\n                    corner_depth[corners1] = depth + 1\n                    done += 1\n        depth += 1\n    with path.open('wb') as fh:\n        corner_depth.tofile(fh)\n    print('cornerprun ready')\n",
  "cornerprun_only": true,
  "dry_run": false,
  "errors": [],
  "executable": "/opt/homebrew/bin/pypy3",
  "expected_table_count": 10,
  "expected_total_size_bytes": 963061264,
  "force": false,
  "inventory": [
    {
      "actual_size_bytes": 69984,
      "exists": true,
      "expected_size_bytes": 69984,
      "name": "conj_twist",
      "path": "/Users/alextoska/Desktop/sgarbas/.codex_external/rubikoptimal_tables/conj_twist",
      "size_matches": true
    },
    {
      "actual_size_bytes": 97320960,
      "exists": true,
      "expected_size_bytes": 97320960,
      "name": "fs24_classidx",
      "path": "/Users/alextoska/Desktop/sgarbas/.codex_external/rubikoptimal_tables/fs24_classidx",
      "size_matches": true
    },
    {
      "actual_size_bytes": 24330240,
      "exists": true,
      "expected_size_bytes": 24330240,
      "name": "fs24_sym",
      "path": "/Users/alextoska/Desktop/sgarbas/.codex_external/rubikoptimal_tables/fs24_sym",
      "size_matches": true
    },
    {
      "actual_size_bytes": 6095456,
      "exists": true,
      "expected_size_bytes": 6095456,
      "name": "fs24_rep",
      "path": "/Users/alextoska/Desktop/sgarbas/.codex_external/rubikoptimal_tables/fs24_rep",
      "size_matches": true
    },
    {
      "actual_size_bytes": 78732,
      "exists": true,
      "expected_size_bytes": 78732,
      "name": "move_twist",
      "path": "/Users/alextoska/Desktop/sgarbas/.codex_external/rubikoptimal_tables/move_twist",
      "size_matches": true
    },
    {
      "actual_size_bytes": 73728,
      "exists": true,
      "expected_size_bytes": 73728,
      "name": "move_flip",
      "path": "/Users/alextoska/Desktop/sgarbas/.codex_external/rubikoptimal_tables/move_flip",
      "size_matches": true
    },
    {
      "actual_size_bytes": 427680,
      "exists": true,
      "expected_size_bytes": 427680,
      "name": "move_slice_sorted",
      "path": "/Users/alextoska/Desktop/sgarbas/.codex_external/rubikoptimal_tables/move_slice_sorted",
      "size_matches": true
    },
    {
      "actual_size_bytes": 1451520,
      "exists": true,
      "expected_size_bytes": 1451520,
      "name": "move_corners",
      "path": "/Users/alextoska/Desktop/sgarbas/.codex_external/rubikoptimal_tables/move_corners",
      "size_matches": true
    },
    {
      "actual_size_bytes": null,
      "exists": false,
      "expected_size_bytes": 833172644,
      "name": "phase1x24_prun",
      "path": "/Users/alextoska/Desktop/sgarbas/.codex_external/rubikoptimal_tables/phase1x24_prun",
      "size_matches": false
    },
    {
      "actual_size_bytes": 40320,
      "exists": true,
      "expected_size_bytes": 40320,
      "name": "cornerprun",
      "path": "/Users/alextoska/Desktop/sgarbas/.codex_external/rubikoptimal_tables/cornerprun",
      "size_matches": true
    }
  ],
  "missing_or_wrong_tables": [
    "phase1x24_prun"
  ],
  "notes": "RubikOptimal is a separate public optimal-solver backend. Its table generation is isolated under .codex_external so importing optimal.solver never writes large pruning files into the repository root.",
  "operation_succeeded": true,
  "package_path": "/opt/miniconda3/lib/python3.12/site-packages",
  "passed": false,
  "ready": false,
  "require_safe": false,
  "run_result": {
    "return_code": 0,
    "runtime_seconds": 0.197459,
    "stderr_tail": "",
    "stdout_tail": "loading move_twist table...\nloading move_flip table...\nloading move_slice_sorted table...\nloading move_corners table...\ncreating cornerprun table...\ncornerprun ready",
    "timed_out": false
  },
  "runtime_seconds": 0.198504,
  "safety": {
    "current_table_bytes": 129848300,
    "expected_total_size_bytes": 963061264,
    "machine": {
      "cpu_count": 8,
      "load_average": [
        10.40673828125,
        17.36474609375,
        15.716796875
      ],
      "table_dir_free_bytes": 36850835456
    },
    "policy": {
      "disk_multiplier": 2.0,
      "load_fraction_limit": 0.5
    },
    "reasons": [
      "current one-minute load average 10.41 is at least 50% of logical CPUs"
    ],
    "remaining_table_bytes": 833212964,
    "safe_to_start": false,
    "table_dir": ".codex_external/rubikoptimal_tables"
  },
  "schema_version": 1,
  "status": "cornerprun_only",
  "table_bytes": 129888620,
  "table_dir": ".codex_external/rubikoptimal_tables",
  "timeout_seconds": 120.0
}
